LICENSE
MANIFEST.in
README.md
setup.py
IBM_BlueUtilities/__init__.py
IBM_BlueUtilities/bluePages.py
IBM_BlueUtilities/bluegroups.py
IBM_BlueUtilities.egg-info/PKG-INFO
IBM_BlueUtilities.egg-info/SOURCES.txt
IBM_BlueUtilities.egg-info/dependency_links.txt
IBM_BlueUtilities.egg-info/not-zip-safe
IBM_BlueUtilities.egg-info/requires.txt
IBM_BlueUtilities.egg-info/top_level.txt