Metadata-Version: 1.0
Name: IBM-BlueUtilities
Version: 1.1
Summary: This Package help to management of bluegroups and retrieve basic information from bluepages.
Home-page: https://github.com/ManuelRuiz39/IBM_DEPENDENCIES
Author: Manuel_Ruiz
Author-email: juan.manuel.ruiz.plascencia@ibm.com
License: Apache License, Version 2.0
Keywords: Bluegroup,BluePages
Platform: UNKNOWN
